lyth/__init__.py
lyth/__main__.py
lyth/cli.py
lyth/compiler/__init__.py
lyth/compiler/scanner.py
lyth-0.0.3.dist-info/AUTHORS.rst
lyth-0.0.3.dist-info/LICENSE
lyth-0.0.3.dist-info/METADATA
lyth-0.0.3.dist-info/WHEEL
lyth-0.0.3.dist-info/entry_points.txt
lyth-0.0.3.dist-info/top_level.txt
lyth-0.0.3.dist-info/RECORD
