Metadata-Version: 2.1
Name: lyth
Version: 0.0.3
Summary: A (monolithic) compiled language
Home-page: https://github.com/gmantelet/python-lyth
Author: Guillaume Mantelet
Author-email: gmantelet@voltigeurnetworks.com
License: BSD-2-Clause
Project-URL: Documentation, https://python-lyth.readthedocs.io/
Project-URL: Changelog, https://python-lyth.readthedocs.io/en/latest/changelog.html
Project-URL: Issue Tracker, https://github.com/gmantelet/python-lyth/issues
Platform: UNKNOWN
Classifier: Development Status :: 5 - Production/Stable
Classifier: Intended Audience :: Developers
Classifier: License :: OSI Approved :: BSD License
Classifier: Operating System :: Unix
Classifier: Operating System :: POSIX
Classifier: Operating System :: Microsoft :: Windows
Classifier: Programming Language :: Python :: 3.7
Classifier: Programming Language :: Python :: 3.8
Classifier: Topic :: Education
Requires-Python: >=3.7
